{
  "codevdb": 101687,
  "name": "Scapelli, The Family \"Mechanic\"",
  "tipo": "ally",
  "source": "cardbase_lib.json",
  "abilities": [],
  "modifiers": {},
  "default_strike": [
    {
      "function": "combat.strike",
      "params": {
        "damage": 2,
        "damage_type": "ranged"
      },
      "text": "Unique mortal with 3 life. 0 strength, 1 bleed.\nScapelli may strike for 2R damage. Once each combat, Scapelli may press to continue combat."
    }
  ],
  "needs_review": true,
  "notes": ""
}
